fun_sentence_splitter/__init__.py
fun_sentence_splitter/sentence_splitter.py
fun_sentence_splitter-0.3.387.dist-info/LICENSE
fun_sentence_splitter-0.3.387.dist-info/METADATA
fun_sentence_splitter-0.3.387.dist-info/WHEEL
fun_sentence_splitter-0.3.387.dist-info/RECORD
