Metadata-Version: 2.3
Name: fun-sentence-splitter
Version: 0.3.387
Summary: A fundamental sentence splitter based on spacy.
License: MIT
Author: Medical AI Engineering
Author-email: engineering@m-ai.rhenus.com
Requires-Python: >3.9,<3.14
Classifier: License :: OSI Approved :: MIT License
Classifier: Programming Language :: Python :: 3
Classifier: Programming Language :: Python :: 3.10
Classifier: Programming Language :: Python :: 3.11
Classifier: Programming Language :: Python :: 3.12
Classifier: Programming Language :: Python :: 3.13
Requires-Dist: spacy (==3.8.7)
